lregression/__init__.py
lregression/lregression.py
regression/__init__.py
regression/regression.py
lregression-1.0.0.dist-info/LICENSE.txt
lregression-1.0.0.dist-info/METADATA
lregression-1.0.0.dist-info/WHEEL
lregression-1.0.0.dist-info/top_level.txt
lregression-1.0.0.dist-info/RECORD
